mxgap/ML.py
mxgap/__init__.py
mxgap/cli.py
mxgap/dos.py
mxgap/features.py
mxgap/input.py
mxgap/structure.py
mxgap/utils.py
mxgap/__pycache__/ML.cpython-312.pyc
mxgap/__pycache__/__init__.cpython-312.pyc
mxgap/__pycache__/cli.cpython-312.pyc
mxgap/__pycache__/dos.cpython-312.pyc
mxgap/__pycache__/features.cpython-312.pyc
mxgap/__pycache__/input.cpython-312.pyc
mxgap/__pycache__/structure.cpython-312.pyc
mxgap/__pycache__/utils.cpython-312.pyc
mxgap/models/MODELS_LIST.txt
mxgap/models/NORM_INFO.txt
mxgap/models/README.md
mxgap/models/models/GBC
mxgap/models/models/GBC_notDOS
mxgap/models/models/GBR
mxgap/models/models/GBR_edges
mxgap/models/models/GBR_edges_notDOS
mxgap/models/models/GBR_notDOS
mxgap/models/models/GBR_onlygap
mxgap/models/models/GBR_onlygap_notDOS
mxgap/models/models/KRR
mxgap/models/models/KRR_edges
mxgap/models/models/KRR_edges_notDOS
mxgap/models/models/KRR_notDOS
mxgap/models/models/KRR_onlygap
mxgap/models/models/KRR_onlygap_notDOS
mxgap/models/models/LR
mxgap/models/models/LR_notDOS
mxgap/models/models/MLPC
mxgap/models/models/MLPC_notDOS
mxgap/models/models/MLPR
mxgap/models/models/MLPR_edges
mxgap/models/models/MLPR_edges_notDOS
mxgap/models/models/MLPR_notDOS
mxgap/models/models/MLPR_onlygap
mxgap/models/models/MLPR_onlygap_notDOS
mxgap/models/models/RFC
mxgap/models/models/RFC_notDOS
mxgap/models/models/RFR
mxgap/models/models/RFR_edges
mxgap/models/models/RFR_edges_notDOS
mxgap/models/models/RFR_notDOS
mxgap/models/models/RFR_onlygap
mxgap/models/models/RFR_onlygap_notDOS
mxgap/models/models/SVC
mxgap/models/models/SVC_notDOS
mxgap/models/models/SVR
mxgap/models/models/SVR_edges
mxgap/models/models/SVR_edges_notDOS
mxgap/models/models/SVR_notDOS
mxgap/models/models/SVR_onlygap
mxgap/models/models/SVR_onlygap_notDOS
mxgap/test/test_.py
mxgap/test/__pycache__/test_.cpython-312-pytest-8.3.3.pyc
mxgap/test/examples/La2C1Cl2/CONTCAR
mxgap/test/examples/La2C1Cl2/DOSCAR
mxgap/test/examples/La2C1Cl2/contcar_array.npy
mxgap-0.6.dist-info/LICENSE
mxgap-0.6.dist-info/METADATA
mxgap-0.6.dist-info/WHEEL
mxgap-0.6.dist-info/entry_points.txt
mxgap-0.6.dist-info/top_level.txt
mxgap-0.6.dist-info/RECORD
