Metadata-Version: 2.2
Name: mxgap
Version: 0.6
Summary: ML models to predict terminated MXene bandgaps.
Home-page: https://github.com/diegonti/mxgap
Author: Diego Ontiveros
Author-email: diego.ontiveros@ub.edu
License: MIT
Classifier: Programming Language :: Python :: 3
Classifier: License :: OSI Approved :: MIT License
Classifier: Operating System :: OS Independent
Classifier: Topic :: Scientific/Engineering :: Chemistry
Classifier: Topic :: Software Development :: Libraries :: Python Modules
Requires-Python: >=3.9
License-File: LICENSE
Requires-Dist: scikit-learn==1.4.1.post1
Requires-Dist: numpy
Requires-Dist: ase
Requires-Dist: pymatgen
Requires-Dist: pytest
